myscale_telemetry/__init__.py
myscale_telemetry/consumer.py
myscale_telemetry/handler.py
myscale_telemetry/span_data.py
myscale_telemetry/task_manager.py
originhub_myscale_telemetry-0.3.3.dist-info/LICENSE
originhub_myscale_telemetry-0.3.3.dist-info/METADATA
originhub_myscale_telemetry-0.3.3.dist-info/WHEEL
originhub_myscale_telemetry-0.3.3.dist-info/top_level.txt
originhub_myscale_telemetry-0.3.3.dist-info/RECORD
