Metadata-Version: 2.2
Name: originhub-myscale-telemetry
Version: 0.3.3
Summary: Open-source observability for your LLM application.
Home-page: https://github.com/OriginHubAI/myscale-telemetry
Author: Hao Lou
Author-email: louh@yuanshu.com
Classifier: Programming Language :: Python :: 3
Classifier: License :: OSI Approved :: MIT License
Classifier: Operating System :: OS Independent
Requires-Python: >=3.10
License-File: LICENSE
Requires-Dist: backoff>=2.2.1
Requires-Dist: langchain~=0.3.19
Requires-Dist: langchain-community~=0.3.18
Requires-Dist: clickhouse-connect>=0.7
Requires-Dist: langchain-openai~=0.3.7
Requires-Dist: tiktoken>=0.7.0
Dynamic: author
Dynamic: author-email
Dynamic: classifier
Dynamic: description
Dynamic: description-content-type
Dynamic: home-page
Dynamic: requires-dist
Dynamic: requires-python
Dynamic: summary
